{
    "jobName": "bl-release",
    "lambdaNamePrefix": "BL",
    "shufflingBucket": "serverless-mapreduce-storage",
    "inputSourceType": "s3",
    "inputSource": "serverless-mapreduce-storage",
    "inputPrefix": "testing_partitioned",
    "inputKeyNameDynamoDB": "record_id",
    "inputColumnNameDynamoDB": "information",
    "outputSourceType": "s3",
    "outputSource": "serverless-mapreduce-storage",
    "outputPrefix": "output",
    "outputKeyNameDynamoDB": "ip",
    "outputColumnNameDynamoDB": "revenue",
    "useCombine": false,
    "numReducers": 4,
    "localTesting": true,
    "localTestingInputPath": "../../input_data/testing_partitioned/s3/",
    "serverlessDriver": false
}
